{
    "entities": [
        {
            "name": "Mostra",
            "attributes": [
                {
                    "name": "Codice",
                    "is_pk": true
                },
                {
                    "name": "Titolo",
                    "is_pk": false
                },
                {
                    "name": "DataIn",
                    "is_pk": false
                },
                {
                    "name": "DataFine",
                    "is_pk": false
                }
            ]
        },
        {
            "name": "Esposizione",
            "attributes": [
                {
                    "name": "fk_mostra",
                    "is_pk": true
                },
                {
                    "name": "fk_quadro",
                    "is_pk": true
                }
            ]
        },
        {
            "name": "Quadro",
            "attributes": [
                {
                    "name": "Codice",
                    "is_pk": true
                },
                {
                    "name": "Autore",
                    "is_pk": false
                },
                {
                    "name": "Anno",
                    "is_pk": false
                }
            ]
        },
        {
            "name": "Sala",
            "attributes": [
                {
                    "name": "Codice",
                    "is_pk": true
                },
                {
                    "name": "Nome",
                    "is_pk": false
                },
                {
                    "name": "Dimensione",
                    "is_pk": false
                }
            ]
        }
    ],
    "relationships": [
        {
            "entity1": "Esposizione",
            "entity2": "Mostra",
            "cardinality": "N:1"
        },
        {
            "entity1": "Esposizione",
            "entity2": "Quadro",
            "cardinality": "N:1"
        },
        {
            "entity1": "Esposizione",
            "entity2": "Sala",
            "cardinality": "N:1"
        }
    ]
}