{
    "entities": [
        {
            "name": "Pezzo",
            "attributes": [
                {
                    "name": "Codice",
                    "is_pk": true
                },
                {
                    "name": "Titolo",
                    "is_pk": false
                }
            ]
        },
        {
            "name": "Musicista",
            "attributes": [
                {
                    "name": "Codice",
                    "is_pk": true
                },
                {
                    "name": "Nome",
                    "is_pk": false
                }
            ]
        },
        {
            "name": "Concerto",
            "attributes": [
                {
                    "name": "Codice",
                    "is_pk": true
                },
                {
                    "name": "Titolo",
                    "is_pk": true
                },
                {
                    "name": "Direttore",
                    "is_pk": false
                }
            ]
        },
        {
            "name": "Replica",
            "attributes": [
                {
                    "name": "Data",
                    "is_pk": true
                },
                {
                    "name": "fk_concerto",
                    "is_pk": true
                }
            ]
        },
        {
            "name": "Sala",
            "attributes": [
                {
                    "name": "Codice",
                    "is_pk": true
                },
                {
                    "name": "Nome",
                    "is_pk": false
                },
                {
                    "name": "Capienza",
                    "is_pk": false
                }
            ]
        },
        {
            "name": "Orchestra",
            "attributes": [
                {
                    "name": "Nome",
                    "is_pk": true
                },
                {
                    "name": "Descrizione",
                    "is_pk": false
                }
            ]
        },
        {
            "name": "Orchestrale",
            "attributes": [
                {
                    "name": "Matricola",
                    "is_pk": true
                },
                {
                    "name": "Nome",
                    "is_pk": false
                },
                {
                    "name": "Cognome",
                    "is_pk": false
                }
            ]
        }
    ],
    "relationships": [
        {
            "entity1": "Pezzo",
            "entity2": "Musicista",
            "cardinality": "N:1"
        },
        {
            "entity1": "Pezzo",
            "entity2": "Concerto",
            "cardinality": "N:N"
        },
        {
            "entity1": "Replica",
            "entity2": "Concerto",
            "cardinality": "N:1"
        },
        {
            "entity1": "Concerto",
            "entity2": "Sala",
            "cardinality": "N:1"
        },
        {
            "entity1": "Orchestra",
            "entity2": "Concerto",
            "cardinality": "1:N"
        },
        {
            "entity1": "Orchestrale",
            "entity2": "Orchestra",
            "cardinality": "N:N",
            "attributes": [
                {
                    "name": "Strumento",
                    "is_pk": false
                }
            ]
        }
    ]
}