{
    "entities": [
        {
            "name": "TEXT",
            "attributes": [
                {
                    "name": "id_materia",
                    "is_pk": true
                }
            ]
        },
        {
            "name": "CORSO",
            "attributes": [
                {
                    "name": "fk_course_of_study",
                    "is_pk": true
                },
                {
                    "name": "fk_materia",
                    "is_pk": true
                }
            ]
        },
        {
            "name": "MATERIA",
            "attributes": [
                {
                    "name": "text_id",
                    "is_pk": true
                }
            ]
        },
        {
            "name": "COURSE OF STUDY",
            "attributes": [
                {
                    "name": "study_course_id",
                    "is_pk": true
                }
            ]
        },
        {
            "name": "PROFESSOR",
            "attributes": [
                {
                    "name": "PROFESSOR_ID",
                    "is_pk": true
                }
            ]
        }
    ],
    "relationships": [
        {
            "entity1": "TEXT",
            "entity2": "CORSO",
            "cardinality": "N:1"
        },
        {
            "entity1": "MATERIA",
            "entity2": "CORSO",
            "cardinality": "1:1"
        },
        {
            "entity1": "CORSO",
            "entity2": "COURSE OF STUDY",
            "cardinality": "N:1"
        },
        {
            "entity1": "MATERIA",
            "entity2": "PROFESSOR",
            "cardinality": "N:1"
        }
    ]
}